{
  "v": 4,
  "entries": {
    "component-react-canvas-confetti--main": {
      "type": "story",
      "id": "component-react-canvas-confetti--main",
      "name": "Main",
      "title": "Component/React Canvas Confetti",
      "importPath": "./storybook/component.stories.tsx",
      "tags": ["story"]
    },
    "presets--main": {
      "type": "story",
      "id": "presets--main",
      "name": "Main",
      "title": "Presets",
      "importPath": "./storybook/presets.stories.tsx",
      "tags": ["story"]
    },
    "presets--fireworks": {
      "type": "story",
      "id": "presets--fireworks",
      "name": "Fireworks",
      "title": "Presets",
      "importPath": "./storybook/presets.stories.tsx",
      "tags": ["story"]
    },
    "presets--crossfire": {
      "type": "story",
      "id": "presets--crossfire",
      "name": "Crossfire",
      "title": "Presets",
      "importPath": "./storybook/presets.stories.tsx",
      "tags": ["story"]
    },
    "presets--snow": {
      "type": "story",
      "id": "presets--snow",
      "name": "Snow",
      "title": "Presets",
      "importPath": "./storybook/presets.stories.tsx",
      "tags": ["story"]
    },
    "presets--realistic": {
      "type": "story",
      "id": "presets--realistic",
      "name": "Realistic",
      "title": "Presets",
      "importPath": "./storybook/presets.stories.tsx",
      "tags": ["story"]
    },
    "presets--explosion": {
      "type": "story",
      "id": "presets--explosion",
      "name": "Explosion",
      "title": "Presets",
      "importPath": "./storybook/presets.stories.tsx",
      "tags": ["story"]
    },
    "presets--pride": {
      "type": "story",
      "id": "presets--pride",
      "name": "Pride",
      "title": "Presets",
      "importPath": "./storybook/presets.stories.tsx",
      "tags": ["story"]
    }
  }
}
